pitop/virtual_hardware/__init__.py
pitop/virtual_hardware/mock_hardware/__init__.py
pitop/virtual_hardware/mock_hardware/vendor/__init__.py
pitop/virtual_hardware/mock_hardware/vendor/Mock/GPIO.py
pitop/virtual_hardware/mock_hardware/vendor/Mock/__init__.py
pitop/virtual_hardware/simulation/__init__.py
pitop/virtual_hardware/simulation/simsprite.py
pitop/virtual_hardware/simulation/simulation.py
pitop/virtual_hardware/simulation/sprites.py
pitop/virtual_hardware/simulation/images/Button.png
pitop/virtual_hardware/simulation/images/Button_pressed.png
pitop/virtual_hardware/simulation/images/LED_green_off.png
pitop/virtual_hardware/simulation/images/LED_green_on.png
pitop/virtual_hardware/simulation/images/LED_red_off.png
pitop/virtual_hardware/simulation/images/LED_red_on.png
pitop/virtual_hardware/simulation/images/LED_yellow_off.png
pitop/virtual_hardware/simulation/images/LED_yellow_on.png
pitop/virtual_hardware/simulation/images/Pitop.png
pitop/virtual_hardware/simulation/images/Readme.md
pitop/virtual_hardware/simulation/images/__init__.py
pitop.virtual_hardware-0.26.1.post1.dist-info/METADATA
pitop.virtual_hardware-0.26.1.post1.dist-info/WHEEL
pitop.virtual_hardware-0.26.1.post1.dist-info/top_level.txt
pitop.virtual_hardware-0.26.1.post1.dist-info/RECORD
