Metadata-Version: 2.1
Name: pitop.virtual-hardware
Version: 0.26.1.post1
Summary: pi-top Python SDK.
Home-page: https://github.com/pi-top/pi-top-Python-SDK
Author: pi-top
Author-email: deb-maintainers@pi-top.com
License: Apache Software License
Keywords: pi-top,raspberrypi,virtual
Platform: ALL
Classifier: Development Status :: 5 - Production/Stable
Classifier: Intended Audience :: Education
Classifier: Intended Audience :: Developers
Classifier: Topic :: Education
Classifier: Topic :: System :: Hardware
Classifier: License :: OSI Approved :: Apache Software License
Classifier: Programming Language :: Python :: 3
Classifier: Programming Language :: Python :: 3.7
Classifier: Programming Language :: Python :: 3.8
Classifier: Programming Language :: Python :: Implementation :: PyPy
Requires-Dist: pitop.core (==0.26.1-1)
Requires-Dist: pygame (<3,>=1.9.6)
Requires-Dist: Pillow (<9.0,>=8.1.2)
